__init__.py
watch_path.py
src/__init__.py
watch_path/__init__.py
watch_path/cli/__init__.py
watch_path-0.1.1.dist-info/LICENSE
watch_path-0.1.1.dist-info/METADATA
watch_path-0.1.1.dist-info/WHEEL
watch_path-0.1.1.dist-info/entry_points.txt
watch_path-0.1.1.dist-info/top_level.txt
watch_path-0.1.1.dist-info/RECORD
