Metadata-Version: 2.1
Name: watch-path
Version: 0.1.1
Summary: Simple wrapper for `os.stat`, calls callback function time-stamp changes
Home-page: https://github.com/python-utilities/watch_path
Author: S0AndS0
Author-email: StrangerThanBland@gmail.com
Classifier: Development Status :: 4 - Beta
Classifier: Intended Audience :: Developers
Classifier: Topic :: Software Development
Classifier: Programming Language :: Python :: 3
Classifier: License :: OSI Approved :: GNU Affero General Public License v3
Classifier: Operating System :: POSIX :: Linux
License-File: LICENSE
